{"cameraMode":{"drawMode":0,"name":"Shaded","section":"Shading Mode"},"sceneLighting":true,"audioPlay":false,"sceneViewState":{"m_AlwaysRefresh":false,"showFog":true,"showSkybox":true,"showFlares":true,"showImageEffects":true,"showParticleSystems":true,"showVisualEffectGraphs":true,"m_FxEnabled":true},"in2DMode":false,"pivot":{"x":-68.03280639648438,"y":20.527835845947267,"z":408.5250549316406},"rotation":{"x":0.08488868176937103,"y":0.9047624468803406,"z":-0.35803040862083437,"w":0.21451754868030549},"size":10.0,"orthographic":false}